multitables/__init__.py
multitables/dataset.py
multitables/dataset_ops.py
multitables/msgpack_ext.py
multitables/numpy_utils.py
multitables/reader.py
multitables/request.py
multitables/resource_wrapper.py
multitables/shared_mem.py
multitables/shared_queue.py
multitables/signals.py
multitables/stage.py
multitables/streamer.py
multitables-2.0.1.dist-info/LICENSE.txt
multitables-2.0.1.dist-info/METADATA
multitables-2.0.1.dist-info/WHEEL
multitables-2.0.1.dist-info/top_level.txt
multitables-2.0.1.dist-info/RECORD
