Metadata-Version: 2.1
Name: multitables
Version: 2.0.1
Summary: High performance parallel reading of HDF5 files using PyTables, multiprocessing, and shared memory.
Home-page: https://github.com/ghcollin/multitables
Author: ghcollin
Author-email: 
License: MIT
Keywords: tables hdf5 parallel concurrent
Platform: UNKNOWN
Classifier: Development Status :: 4 - Beta
Classifier: Intended Audience :: Developers
Classifier: Intended Audience :: Information Technology
Classifier: Intended Audience :: Science/Research
Classifier: License :: OSI Approved :: MIT License
Classifier: Programming Language :: Python :: 2.7
Classifier: Programming Language :: Python :: 3.5
Classifier: Topic :: Database
Classifier: Topic :: Software Development :: Libraries :: Python Modules
Requires-Dist: msgpack (>=0.6.0)
Requires-Dist: numpy
Requires-Dist: tables
Requires-Dist: wrapt
